{
  "name": "Morphous Seadragon - Boosted (Dark)",
  "type": "dark",
  "colors": {
    "focusBorder": "#E9C767",
    "foreground": "#F4F0DA",
    "widget.border": "#ffffff15",
    "selection.background": "#E4EC7935",
    "editor.background": "#1D2C1B",
    "editor.foreground": "#F4F0DA",
    "editor.lineHighlightBackground": "#14191040",
    "editor.lineHighlightBorder": "#00000000",
    "editorCursor.foreground": "#E9C767",
    "editor.selectionBackground": "#E4EC7935",
    "editor.inactiveSelectionBackground": "#E4EC793580",
    "editorLineNumber.foreground": "#7B812A80",
    "editorLineNumber.activeForeground": "#E9C767",
    "sideBar.background": "#141910",
    "sideBar.foreground": "#F4F0DA",
    "sideBar.border": "#ffffff15",
    "sideBarSectionHeader.background": "#1D2C1B80",
    "sideBarSectionHeader.foreground": "#F4F0DA",
    "sideBarTitle.foreground": "#E9C767",
    "activityBar.background": "#1D2C1B",
    "activityBar.foreground": "#E9C767",
    "activityBar.inactiveForeground": "#F4F0DA60",
    "activityBar.border": "#ffffff15",
    "activityBarBadge.background": "#E9C767",
    "activityBarBadge.foreground": "#1D2C1B",
    "statusBar.background": "#1D2C1B",
    "statusBar.foreground": "#F4F0DA",
    "statusBar.border": "#ffffff15",
    "statusBar.noFolderBackground": "#1D2C1B",
    "titleBar.activeBackground": "#1D2C1B",
    "titleBar.activeForeground": "#F4F0DA",
    "titleBar.inactiveBackground": "#1D2C1B",
    "titleBar.inactiveForeground": "#F4F0DA60",
    "titleBar.border": "#ffffff15",
    "editorGroupHeader.tabsBackground": "#1D2C1Bdd",
    "tab.activeBackground": "#1D2C1B",
    "tab.activeForeground": "#F4F0DA",
    "tab.inactiveBackground": "#14191060",
    "tab.inactiveForeground": "#F4F0DA80",
    "tab.border": "#ffffff15",
    "tab.activeBorderTop": "#E9C767",
    "list.activeSelectionBackground": "#E9C76730",
    "list.activeSelectionForeground": "#F4F0DA",
    "list.hoverBackground": "#14191040",
    "list.hoverForeground": "#F4F0DA",
    "list.inactiveSelectionBackground": "#E9C76715",
    "list.inactiveSelectionForeground": "#F4F0DA",
    "list.highlightForeground": "#E9C767",
    "terminal.background": "#1D2C1B",
    "terminal.foreground": "#F4F0DA",
    "terminal.ansiBlack": "#1D2C1B",
    "terminal.ansiRed": "#F1EE83",
    "terminal.ansiGreen": "#E9C767",
    "terminal.ansiYellow": "#55E7DD",
    "terminal.ansiBlue": "#E4EC79",
    "terminal.ansiMagenta": "#F1EE83",
    "terminal.ansiCyan": "#55E7DD",
    "terminal.ansiWhite": "#F4F0DA",
    "input.background": "#141910",
    "input.foreground": "#F4F0DA",
    "input.border": "#ffffff15",
    "input.placeholderForeground": "#F4F0DA60",
    "button.background": "#E9C767",
    "button.foreground": "#1D2C1B",
    "button.hoverBackground": "#E9C767dd"
  },
  "tokenColors": [
    {
      "scope": [
        "comment",
        "punctuation.definition.comment"
      ],
      "settings": {
        "foreground": "#7B812A",
        "fontStyle": "italic"
      }
    },
    {
      "scope": [
        "keyword",
        "keyword.control",
        "keyword.operator.new",
        "keyword.operator.expression",
        "keyword.operator.logical"
      ],
      "settings": {
        "foreground": "#E4EC79",
        "fontStyle": "bold"
      }
    },
    {
      "scope": [
        "storage.type",
        "storage.modifier"
      ],
      "settings": {
        "foreground": "#E4EC79",
        "fontStyle": "italic"
      }
    },
    {
      "scope": [
        "entity.name.function",
        "support.function",
        "keyword.other.special-method",
        "meta.function-call"
      ],
      "settings": {
        "foreground": "#E9C767"
      }
    },
    {
      "scope": [
        "string",
        "punctuation.definition.string",
        "string.template",
        "meta.template.expression"
      ],
      "settings": {
        "foreground": "#55E7DD"
      }
    },
    {
      "scope": [
        "constant.numeric",
        "constant.language",
        "constant.character",
        "constant.other",
        "variable.other.constant"
      ],
      "settings": {
        "foreground": "#F1EE83"
      }
    },
    {
      "scope": [
        "variable",
        "variable.other.readwrite",
        "variable.other.object"
      ],
      "settings": {
        "foreground": "#F4F0DA"
      }
    },
    {
      "scope": [
        "variable.other.property",
        "support.variable.property",
        "meta.object-literal.key",
        "meta.object.member"
      ],
      "settings": {
        "foreground": "#F4F0DA"
      }
    },
    {
      "scope": [
        "variable.parameter",
        "meta.parameter"
      ],
      "settings": {
        "foreground": "#F4F0DAdd",
        "fontStyle": "italic"
      }
    },
    {
      "scope": [
        "punctuation.separator",
        "punctuation.terminator",
        "punctuation.definition.parameters",
        "punctuation.definition.block",
        "punctuation.section",
        "meta.brace"
      ],
      "settings": {
        "foreground": "#F4F0DA80"
      }
    },
    {
      "scope": [
        "keyword.operator"
      ],
      "settings": {
        "foreground": "#F4F0DA"
      }
    },
    {
      "scope": [
        "entity.name.type",
        "entity.name.class",
        "entity.name.namespace",
        "entity.name.scope-resolution",
        "support.type",
        "support.class",
        "support.other.namespace"
      ],
      "settings": {
        "foreground": "#55E7DD",
        "fontStyle": "bold"
      }
    },
    {
      "scope": [
        "entity.other.inherited-class"
      ],
      "settings": {
        "foreground": "#E9C767"
      }
    },
    {
      "scope": [
        "entity.name.tag",
        "punctuation.definition.tag"
      ],
      "settings": {
        "foreground": "#E4EC79"
      }
    },
    {
      "scope": [
        "entity.other.attribute-name"
      ],
      "settings": {
        "foreground": "#E9C767"
      }
    },
    {
      "scope": [
        "meta.diff",
        "meta.diff.header"
      ],
      "settings": {
        "foreground": "#7B812A"
      }
    },
    {
      "scope": "markup.deleted",
      "settings": {
        "foreground": "#F1EE83"
      }
    },
    {
      "scope": "markup.inserted",
      "settings": {
        "foreground": "#E9C767"
      }
    },
    {
      "scope": "markup.changed",
      "settings": {
        "foreground": "#55E7DD"
      }
    },
    {
      "scope": [
        "markup.heading",
        "markup.heading.setext",
        "punctuation.definition.heading"
      ],
      "settings": {
        "foreground": "#E9C767",
        "fontStyle": "bold"
      }
    },
    {
      "scope": "markup.bold",
      "settings": {
        "fontStyle": "bold"
      }
    },
    {
      "scope": "markup.italic",
      "settings": {
        "fontStyle": "italic"
      }
    },
    {
      "scope": [
        "markup.inline.raw",
        "markup.raw.block"
      ],
      "settings": {
        "foreground": "#55E7DD"
      }
    },
    {
      "scope": [
        "string.other.link.title",
        "string.other.link.description"
      ],
      "settings": {
        "foreground": "#E9C767"
      }
    },
    {
      "scope": "markup.underline.link",
      "settings": {
        "foreground": "#7B812A",
        "fontStyle": "underline"
      }
    },
    {
      "scope": [
        "punctuation.definition.list"
      ],
      "settings": {
        "foreground": "#E4EC79"
      }
    },
    {
      "scope": [
        "markup.quote",
        "punctuation.definition.quote"
      ],
      "settings": {
        "foreground": "#7B812A",
        "fontStyle": "italic"
      }
    }
  ]
}
